klusterinfo/__init__.py
klusterinfo/api.py
klusterinfo/kubernetes_units.txt
klusterinfo-0.1.1.dist-info/METADATA
klusterinfo-0.1.1.dist-info/WHEEL
klusterinfo-0.1.1.dist-info/entry_points.txt
klusterinfo-0.1.1.dist-info/RECORD
