Metadata-Version: 2.4
Name: klusterinfo
Version: 0.1.1
Author-email: Steinn Eldjárn Sigurðarson <steinnes@gmail.com>
Requires-Python: >=3.10
Requires-Dist: click<8.0,>=7.0
Requires-Dist: pint<0.25,>=0.24
Requires-Dist: pykubeks==0.1.0
Provides-Extra: dev
Requires-Dist: black>=18.3a0; extra == 'dev'
